docling/__init__.py
docling/document_converter.py
docling/document_extractor.py
docling/exceptions.py
docling/py.typed
docling/backend/__init__.py
docling/backend/abstract_backend.py
docling/backend/asciidoc_backend.py
docling/backend/csv_backend.py
docling/backend/docling_parse_backend.py
docling/backend/docling_parse_v2_backend.py
docling/backend/docling_parse_v4_backend.py
docling/backend/html_backend.py
docling/backend/image_backend.py
docling/backend/md_backend.py
docling/backend/mets_gbs_backend.py
docling/backend/msexcel_backend.py
docling/backend/mspowerpoint_backend.py
docling/backend/msword_backend.py
docling/backend/noop_backend.py
docling/backend/pdf_backend.py
docling/backend/pypdfium2_backend.py
docling/backend/webvtt_backend.py
docling/backend/docx/__init__.py
docling/backend/docx/drawingml/utils.py
docling/backend/docx/latex/__init__.py
docling/backend/docx/latex/latex_dict.py
docling/backend/docx/latex/omml.py
docling/backend/json/__init__.py
docling/backend/json/docling_json_backend.py
docling/backend/xml/__init__.py
docling/backend/xml/jats_backend.py
docling/backend/xml/uspto_backend.py
docling/chunking/__init__.py
docling/cli/__init__.py
docling/cli/main.py
docling/cli/models.py
docling/cli/tools.py
docling/datamodel/__init__.py
docling/datamodel/accelerator_options.py
docling/datamodel/asr_model_specs.py
docling/datamodel/backend_options.py
docling/datamodel/base_models.py
docling/datamodel/document.py
docling/datamodel/extraction.py
docling/datamodel/layout_model_specs.py
docling/datamodel/pipeline_options.py
docling/datamodel/pipeline_options_asr_model.py
docling/datamodel/pipeline_options_vlm_model.py
docling/datamodel/settings.py
docling/datamodel/vlm_model_specs.py
docling/experimental/__init__.py
docling/experimental/datamodel/__init__.py
docling/experimental/datamodel/table_crops_layout_options.py
docling/experimental/datamodel/threaded_layout_vlm_pipeline_options.py
docling/experimental/models/__init__.py
docling-2.71.0.dist-info/licenses/LICENSE
docling-2.71.0.dist-info/METADATA
docling-2.71.0.dist-info/WHEEL
docling-2.71.0.dist-info/entry_points.txt
docling-2.71.0.dist-info/top_level.txt
docling-2.71.0.dist-info/RECORD
